permguard/__about__.py
permguard/__init__.py
permguard/az_client.py
permguard/az_config.py
permguard/az/azreq/builder_action.py
permguard/az/azreq/builder_context.py
permguard/az/azreq/builder_evaluation.py
permguard/az/azreq/builder_principal.py
permguard/az/azreq/builder_request_atomic.py
permguard/az/azreq/builder_request_composed.py
permguard/az/azreq/builder_resource.py
permguard/az/azreq/builder_subject.py
permguard/az/azreq/model.py
permguard/internal/az/azreq/grpc/v1/pdp_client.py
permguard/internal/az/azreq/grpc/v1/pdp_pb2.py
permguard/internal/az/azreq/grpc/v1/pdp_pb2_grpc.py
permguard-0.0.19.dist-info/METADATA
permguard-0.0.19.dist-info/WHEEL
permguard-0.0.19.dist-info/licenses/LICENSE
permguard-0.0.19.dist-info/licenses/NOTICE.md
permguard-0.0.19.dist-info/RECORD
