Metadata-Version: 2.4
Name: permguard
Version: 0.0.19
Summary: The official Python SDK for Permguard (https://www.permguard.com)
Project-URL: Documentation, https://www.permguard.com
Project-URL: Source, https://github.com/permguard/permguard
Author-email: "Nitro Agility S.r.l." <opensource@permguard.com>
License-Expression: Apache-2.0
License-File: LICENSE
License-File: NOTICE.md
Keywords: Nitro Agility S.r.l.,Permguard
Classifier: Development Status :: 5 - Production/Stable
Classifier: Intended Audience :: Developers
Classifier: License :: OSI Approved :: Apache Software License
Classifier: Natural Language :: English
Classifier: Operating System :: OS Independent
Classifier: Programming Language :: Python
Classifier: Programming Language :: Python :: 3.8
Classifier: Programming Language :: Python :: 3.9
Classifier: Programming Language :: Python :: 3.10
Classifier: Programming Language :: Python :: 3.11
Classifier: Programming Language :: Python :: Implementation :: CPython
Classifier: Programming Language :: Python :: Implementation :: PyPy
Classifier: Topic :: Software Development :: Libraries :: Python Modules
Requires-Python: >=3.8
Requires-Dist: deepdiff~=8.0.1
Requires-Dist: grpcio~=1.70.0
Requires-Dist: protobuf~=5.29.3
Requires-Dist: pydantic~=2.10.6
Requires-Dist: pytz~=2023.3
Requires-Dist: tzlocal~=4.3
